apache_sedona-1.8.1.dist-info/RECORD
apache_sedona-1.8.1.dist-info/WHEEL
apache_sedona-1.8.1.dist-info/top_level.txt
apache_sedona-1.8.1.dist-info/METADATA
sedona/version.py
sedona/__init__.py
sedona/exceptions.py
sedona/maps/SedonaKepler.py
sedona/maps/__init__.py
sedona/maps/SedonaPyDeck.py
sedona/stac/client.py
sedona/stac/__init__.py
sedona/stac/collection_client.py
sedona/core/__init__.py
sedona/core/formatMapper/geo_json_reader.py
sedona/core/formatMapper/__init__.py
sedona/core/formatMapper/shapefileParser/__init__.py
sedona/core/formatMapper/shapefileParser/shape_file_reader.py
sedona/core/enums/__init__.py
sedona/core/SpatialRDD/__init__.py
sedona/core/jvm/config.py
sedona/core/jvm/__init__.py
sedona/core/geom/geography.py
sedona/core/geom/circle.py
sedona/core/geom/__init__.py
sedona/core/geom/envelope.py
sedona/core/spatialOperator/__init__.py
sedona/flink/__init__.py
sedona/flink/context.py
sedona/utils/adapter.py
sedona/utils/__init__.py
sedona/utils/spatial_rdd_parser.py
sedona/utils/structured_adapter/__init__.py
sedona/geoarrow/__init__.py
sedona/raster_utils/SedonaUtils.py
sedona/raster_utils/__init__.py
sedona/register/__init__.py
sedona/db/dbapi.py
sedona/db/__init__.py
sedona/db/telemetry.py
sedona/db/testing.py
sedona/doc/conf.py
sedona/raster/data_buffer.py
sedona/raster/__init__.py
sedona/raster/raster_serde.py
sedona/raster/sedona_raster.py
sedona/raster/sample_model.py
sedona/raster/awt_raster.py
sedona/raster/meta.py
sedona/stats/__init__.py
sedona/stats/hotspot_detection/getis_ord.py
sedona/stats/hotspot_detection/__init__.py
sedona/stats/hotspot_detection/getis_ord/__init__.py
sedona/stats/clustering/__init__.py
sedona/stats/clustering/dbscan/__init__.py
sedona/stats/weighting/__init__.py
sedona/stats/outlier_detection/__init__.py
sedona/stats/outlier_detection/local_outlier_factor/__init__.py
sedona/spark/SedonaContext.py
sedona/spark/__init__.py
sedona/spark/maps/SedonaMapUtils.py
sedona/spark/maps/SedonaKepler.py
sedona/spark/maps/__init__.py
sedona/spark/maps/SedonaPyDeck.py
sedona/spark/stac/client.py
