Metadata-Version: 2.1
Name: apache-sedona
Version: 1.8.1
Summary: Apache Sedona is a cluster computing system for processing large-scale spatial data
Author-email: Apache Sedona <dev@sedona.apache.org>
License: Apache-2.0
Project-URL: HomePage, https://sedona.apache.org
Project-URL: Documentation, https://sedona.apache.org
Project-URL: Source code, https://github.com/apache/sedona
Project-URL: Bug Reports, https://issues.apache.org/jira/projects/SEDONA
Classifier: Programming Language :: Python :: 3
Classifier: License :: OSI Approved :: Apache Software License
Requires-Python: >=3.8
Requires-Dist: attrs
Requires-Dist: shapely>=1.7.0
Provides-Extra: all
Requires-Dist: pyspark<4.1.0,>=3.4.0; extra == "all"
Requires-Dist: geopandas; extra == "all"
Requires-Dist: pydeck==0.8.0; extra == "all"
Requires-Dist: keplergl==0.3.2; extra == "all"
Requires-Dist: rasterio>=1.2.10; extra == "all"
Provides-Extra: db
Requires-Dist: sedonadb[geopandas]; python_version >= "3.9" and extra == "db"
Provides-Extra: flink
Requires-Dist: apache-flink>=1.19.0; extra == "flink"
Provides-Extra: kepler-map
Requires-Dist: geopandas; extra == "kepler-map"
Requires-Dist: keplergl==0.3.2; extra == "kepler-map"
Provides-Extra: pydeck-map
Requires-Dist: geopandas; extra == "pydeck-map"
Requires-Dist: pydeck==0.8.0; extra == "pydeck-map"
Provides-Extra: spark
Requires-Dist: pyspark<4.1.0,>=3.4.0; extra == "spark"
